setup.py
perflogster/PerformanceLogster.py
perflogster/__init__.py
perflogster.egg-info/PKG-INFO
perflogster.egg-info/SOURCES.txt
perflogster.egg-info/dependency_links.txt
perflogster.egg-info/not-zip-safe
perflogster.egg-info/requires.txt
perflogster.egg-info/top_level.txt