Metadata-Version: 1.1
Name: perflogster
Version: 0.0.3
Summary: Custom performance log parser
Home-page: https://github.com/3fs/perflogster
Author: 3fs
Author-email: UNKNOWN
License: GPL3
Download-URL: https://github.com/3fs/perflogster/releases/tag/0.0.2
Platform: UNKNOWN
